gimie/__init__.py
gimie/cli.py
gimie/extractors/__init__.py
gimie/extractors/abstract.py
gimie/extractors/common/queries.py
gimie/extractors/git.py
gimie/extractors/github.py
gimie/extractors/gitlab.py
gimie/graph/__init__.py
gimie/graph/namespaces.py
gimie/graph/operations.py
gimie/io.py
gimie/models.py
gimie/parsers/__init__.py
gimie/parsers/abstract.py
gimie/parsers/cff.py
gimie/parsers/license/__init__.py
gimie/parsers/license/data/spdx_licenses.csv
gimie/parsers/license/data/tfidf_matrix.npz
gimie/parsers/license/data/tfidf_vectorizer.json
gimie/project.py
gimie/utils/text_processing.py
gimie/utils/uri.py
gimie-0.7.2.dist-info/LICENSE
gimie-0.7.2.dist-info/METADATA
gimie-0.7.2.dist-info/WHEEL
gimie-0.7.2.dist-info/entry_points.txt
gimie-0.7.2.dist-info/RECORD
