Metadata-Version: 2.1
Name: gimie
Version: 0.7.2
Summary: Extract structured metadata from git repositories.
Home-page: https://github.com/sdsc-ordes/gimie
License: Apache-2.0
Keywords: metadata,git,extraction,linked-data
Author: Swiss Data Science Center
Author-email: contact@datascience.ch
Requires-Python: >=3.9,<4.0
Classifier: Development Status :: 4 - Beta
Classifier: Intended Audience :: Developers
Classifier: Intended Audience :: Science/Research
Classifier: License :: OSI Approved :: Apache Software License
Classifier: Operating System :: OS Independent
Classifier: Programming Language :: Python :: 3
Classifier: Programming Language :: Python :: 3.9
Classifier: Programming Language :: Python :: 3.10
Classifier: Programming Language :: Python :: 3.11
Classifier: Programming Language :: Python :: 3.12
Requires-Dist: PyDriller (>=2.5,<3.0)
Requires-Dist: calamus (>=0.4.2,<0.5.0)
Requires-Dist: gitpython (>=3.1.35)
Requires-Dist: numpy (>=1.26.1,<2.0.0)
Requires-Dist: pydantic (>=2.4.2,<3.0.0)
Requires-Dist: python-dateutil (>=2.8.2,<3.0.0)
Requires-Dist: python-dotenv (>=0.21.1,<0.22.0)
Requires-Dist: pyyaml (>=6.0.2,<7.0.0)
Requires-Dist: requests (>=2.28.2,<3.0.0)
Requires-Dist: scipy (>=1.11.3,<2.0.0)
Requires-Dist: spdx-license-list (>=3.22,<4.0)
Requires-Dist: typer (>=0.7.0,<0.8.0)
